DiscUtils.py
DiscUtils-1.7.92.dist-info/METADATA
DiscUtils-1.7.92.dist-info/WHEEL
DiscUtils-1.7.92.dist-info/top_level.txt
DiscUtils-1.7.92.dist-info/RECORD
