Metadata-Version: 2.1
Name: DiscUtils
Version: 1.7.92
Home-page: https://github.com/mosaiyka/DiscUtils
Author: mosaiyka
Author-email: artmonuzartemonuz@gmail.com
Keywords: discord discum discord.py-self DiscUtils discutils DiscordUtils
Requires-Dist: requests
Requires-Dist: websocket-client
Requires-Dist: websockets
Requires-Dist: asyncio
Requires-Dist: colorama
